[
  {
    "en": "Everything will be all right",
    "ru": "Все будет хорошо"
  },
  {
    "en": "You are an amazing creature",
    "ru": "Ты - замечательное создание"
  },
  {
    "en": "Everything will work out. Definitely!",
    "ru": "Все получится. Однозначно!"
  },
  {
    "en": "Never give up",
    "ru": "Никогда не сдавайся"
  },
  {
    "en": "Always find reasons for joy and gratitude",
    "ru": "Всегда находи поводы для радости и благодарности"
  },
  {
    "en": "Don't forget that rest is very important",
    "ru": "Не забывай, что отдых очень важен"
  },
  {
    "en": "Look after yourself",
    "ru": "Береги себя"
  },
  {
    "en": "Remember that health is the most important thing",
    "ru": "Помни, что здоровье - это самое важное"
  },
  {
    "en": "In any situation be kind",
    "ru": "В любой ситуации поступай по-доброму"
  },
  {
    "en": "Keep positive thinking",
    "ru": "Сохраняй позитивное мышление"
  },
  {
    "en": "Keep your mind clean",
    "ru": "Храни свой разум чистым"
  },
  {
    "en": "Create beautiful and pure thoughts",
    "ru": "Создавай красивые и чистые мысли"
  },
  {
    "en": "Find joy in anything you do",
    "ru": "Находи радость в любом деле"
  },
  {
    "en": "May your soul be full of love and joy",
    "ru": "Пусть твоя душа будет полна любви и радости"
  },
  {
    "en": "May all beings be happy",
    "ru": "Пусть все существа будут счастливы"
  },
  {
    "en": "You can create wonderful things",
    "ru": "Ты можешь создавать чудесные вещи"
  },
  {
    "en": "You're on the right track",
    "ru": "Ты на правильном пути"
  },
  {
    "en": "Take your time. All in good time",
    "ru": "Не спеши. Всему свое время"
  },
  {
    "en": "It's all good. Everything is going as it should",
    "ru": "Все хорошо. Все идет, как надо"
  },
  {
    "en": "In any case, everything will be fine",
    "ru": "В любом случае все будет хорошо"
  },
  {
    "en": "You are a good person",
    "ru": "Ты хороший человек"
  },
  {
    "en": "Think good thoughts",
    "ru": "Думай о хорошем"
  },
  {
    "en": "In any situation find something good",
    "ru": "В любой ситуации находи что-то хорошее"
  },
  {
    "en": "Prioritize, remember the most important things",
    "ru": "Расставляй приоритеты, помни о самом важном"
  },
  {
    "en": "Smile more often",
    "ru": "Улыбайся чаще"
  },
  {
    "en": "Keep your heart kind",
    "ru": "Храни сердце добрым"
  },
  {
    "en": "Take care of your loved ones",
    "ru": "Заботься о любимых"
  },
  {
    "en": "You can do it. Just keep going",
    "ru": "Ты все сможешь. Просто продолжай"
  },
  {
    "en": "You will certainly succeed",
    "ru": "Тебя определенно ждет успех"
  },
  {
    "en": "Small steps will lead to a big goal",
    "ru": "Маленькие шаги приведут к большой цели"
  },
  {
    "en": "Diligence and continuity will lead to success",
    "ru": "Усердие и непрерывность приведут к успеху"
  },
  {
    "en": "May the Force be with you",
    "ru": "Да пребудет с тобой Сила"
  },
  {
    "en": "Life is beautiful. Enjoy the ride",
    "ru": "Жизнь прекрасна. Наслаждайся дорогой"
  },
  {
    "en": "Enjoy every moment",
    "ru": "Наслаждайся каждым моментом"
  },
  {
    "en": "Follow your heart",
    "ru": "Следуй за своим сердцем"
  },
  {
    "en": "Follow your dreams",
    "ru": "Следуй за своими мечтами"
  },
  {
    "en": "Work hard. Dream big",
    "ru": "Работай усердно. Мечтай по-крупному"
  },
  {
    "en": "Don't worry, be happy",
    "ru": "Не волнуйся, будь счастлив"
  },
  {
    "en": "Dreams come true",
    "ru": "Мечты сбываются"
  },
  {
    "en": "Be someone who makes you happy",
    "ru": "Будь тем, кто делает тебя счастливым"
  },
  {
    "en": "Trust yourself",
    "ru": "Доверяй себе"
  },
  {
    "en": "Keep your balance",
    "ru": "Держи равновесие"
  },
  {
    "en": "Believe in the best",
    "ru": "Верь в лучшее"
  },
  {
    "en": "Everything is getting better and better every day",
    "ru": "С каждым днем все становится лучше и лучше"
  },
  {
    "en": "It's going to be a beautiful day today",
    "ru": "Сегодня будет прекрасный день"
  }
]
